memory_bank_server/__init__.py
memory_bank_server/__main__.py
memory_bank_server/run_server.py
memory_bank_server/core/__init__.py
memory_bank_server/core/context.py
memory_bank_server/core/memory_bank.py
memory_bank_server/server/__init__.py
memory_bank_server/server/direct_access.py
memory_bank_server/server/fastmcp_integration.py
memory_bank_server/server/memory_bank_server.py
memory_bank_server/server/tool_schemas.py
memory_bank_server/services/__init__.py
memory_bank_server/services/context_service.py
memory_bank_server/services/repository_service.py
memory_bank_server/services/storage_service.py
mseep_claude_desktop_memory_bank-0.1.0.dist-info/licenses/LICENSE
mseep_claude_desktop_memory_bank-0.1.0.dist-info/METADATA
mseep_claude_desktop_memory_bank-0.1.0.dist-info/WHEEL
mseep_claude_desktop_memory_bank-0.1.0.dist-info/entry_points.txt
mseep_claude_desktop_memory_bank-0.1.0.dist-info/top_level.txt
mseep_claude_desktop_memory_bank-0.1.0.dist-info/RECORD
