Metadata-Version: 2.4
Name: mseep-claude-desktop-memory-bank
Version: 0.1.0
Summary: Memory Bank MCP Server for Claude Desktop
Author: mseep
Requires-Python: >=3.8
License-File: LICENSE
Requires-Dist: mcp==1.6.0
Requires-Dist: httpx>=0.20.0
Requires-Dist: gitpython>=3.1.0
Dynamic: author
Dynamic: description
Dynamic: description-content-type
Dynamic: license-file
Dynamic: requires-dist
Dynamic: requires-python
Dynamic: summary
